README.md
setup.cfg
setup.py
petrovna/__init__.py
petrovna.egg-info/PKG-INFO
petrovna.egg-info/SOURCES.txt
petrovna.egg-info/dependency_links.txt
petrovna.egg-info/not-zip-safe
petrovna.egg-info/top_level.txt