Metadata-Version: 2.1
Name: petrovna
Version: 1.0.2
Summary: Validatee bic, inn, kpp, ogrn, ogrnip, corr. account, account number, snils
Home-page: https://example.com
Author: KODE LLC
License: UNKNOWN
Platform: Any
Classifier: Intended Audience :: Developers
Classifier: Programming Language :: Python :: 3.7
Classifier: Operating System :: OS Independent
